{
    "report_title_prefix": "Period Report: Last",
    "report_title_days": "days",
    "report_title_date_separator": "to",
    "total_time_label": "Total Time Recorded",
    "actual_days_label": "Actual Days with Records",
    "no_records_message": "No time records found in this period.",
    "invalid_days_message": "Number of days to query must be positive.",
    "main_font": "Noto Serif SC",
    "cjk_main_font": "Noto Serif SC",
    "base_font_size": 12,
    "report_title_font_size": 18,
    "category_title_font_size": 16,
    "margin_in": 1.0,
    "list_top_sep_pt": 0,
    "list_item_sep_ex": -0.5
}